nnkutils/__init__.py
nnkutils/init_pkg/__init__.py
nnkutils/init_pkg/__main__.py
nnkutils/plot/__init__.py
nanako_utils-0.0.2.dist-info/LICENSE
nanako_utils-0.0.2.dist-info/METADATA
nanako_utils-0.0.2.dist-info/WHEEL
nanako_utils-0.0.2.dist-info/top_level.txt
nanako_utils-0.0.2.dist-info/RECORD
